{
  "id": "20003",
  "description": "User based - Colaborative Filtering - Proposal profile model with genre hierarchy - Pearson similarity - Mahout framework - Mov1M dataset - 100% sparsity level - engine settings.",
  "engineType": "br.ufsc.lapesd.orbs.core.ProposalEngine",
  "engineName": "ORBS_Genre100",
  "datasource": {
    "params" : {
      "sourceLocation": ["C:/Users/Juarez Sacenti/Documents/SRO-dev/datasets/ml-1m/ratings.dat"],
      "enclosure": "\"",
      "delimiter": "::",
      "hasHeaderLine": false,
      "hasEventTimestamp": true
    }
  },
  "preparator": {
    "params" : {
      "contextOntologyParams": {
        "ontologyURI": "http://www.lapesd.inf.ufsc.br/projetos/sro/mov1m-sro.owl",
        "ontologyModelSpec": "OWL_DL_MEM",
  	    "tripleStore": "Text",
        "tripleStoreDirectory": "C:/Users/Juarez Sacenti/Desktop/",
        "repositoryName": "mov1m-sro.owl",
        "importedOntologyParams": [
          {
            "ontologyURI": "http://www.movieontology.org/2009/11/09/movieontology.owl",
            "fileLocation": "src/resources/main/importedOntologies/movieontology.owl",
            "fileFormat": "RDF/XML"
          },
          {
            "ontologyURI": "http://www.lapesd.inf.ufsc.br/ontology/2.0.0/recont.owl",
            "fileLocation": "src/resources/main/importedOntologies/recont.owl",
            "fileFormat": "RDF/XML"
          },
          {
            "ontologyURI": "http://www.lapesd.inf.ufsc.br/projetos/sro/contextOntology.owl",
            "fileLocation": "src/resources/main/importedOntologies/contextOntology.owl",
            "fileFormat": "RDF/XML"
          }
        ]
   	  },
   	  "annotationSources": [
       	  {
            "name": "br.ufsc.lapesd.orbs.core.TTLAnnotationSource",
            "sourceLocation": ["src/resources/main/example/datasets/Mov1M/Mov1M-itemGenre.ttl"],
            "enclosure": "",
            "delimiter": " ",
            "hasHeaderLine": false,
            "hasEventTimestamp": false
          }
      ],
      "propertiesOfInterest": [ 
          "http://www.lapesd.inf.ufsc.br/projetos/sro/mov1m-sro.owl#genreHierarchy",     
      ],
  	  "semanticExpansionerParams": {
  	    "datasetScope": [ 
          {
  	        "datasetScopeName": "dbpedia.org",
            "datasetScopeEndpoint": "http://dbpedia.org/sparql",
            "datasetScopeProperties": [ 
              {
                "property": "http://www.w3.org/1999/02/22-rdf-syntax-ns#type",
                "isTransitive": false
              },
              {
                "property": "http://www.w3.org/2000/01/rdf-schema#subClassOf",
                "isTransitive": true
              }
            ]
          }
  	    ]
  	  },
  	  "hierarchyBuilderParams": {
  	    "hierarchiesParams": [ 
          { 
            "hierarchyProperty": "http://www.lapesd.inf.ufsc.br/projetos/sro/mov1m-sro.owl#genreHierarchy",
            "mappingProperties": [
              {
                "property": "http://www.movieontology.org/2009/10/01/movieontology.owl#belongsToGenre",
                "isTransitive": false
              },
              {
                "property": "http://www.w3.org/1999/02/22-rdf-syntax-ns#type",
                "isTransitive": false
              },
              {
                "property": "http://www.w3.org/2000/01/rdf-schema#subClassOf",
                "isTransitive": true
              }
            ]
          }
  	    ],
  	    "countersParams": [
  	      {
  	        "counterType": "userCounter",
  	        "userType": "http://www.lapesd.inf.ufsc.br/ontology/recont.owl#Audience",
  	        "userProperty": "http://www.lapesd.inf.ufsc.br/ontology/recont.owl#doInteraction",
  	        "countedProperty": "http://www.lapesd.inf.ufsc.br/ontology/recont.owl#happensWith",
	        "hierarchyProperty": "http://www.lapesd.inf.ufsc.br/projetos/sro/mov1m-sro.owl#genreHierarchy",
	        "directHitProperty": "http://www.lisa.inf.ufsc.br/sedim-ontology#directHitsOfAudience",
	        "indirectHitProperty": "http://www.lisa.inf.ufsc.br/sedim-ontology#indirectHitsOfAudience"	          
  	      }
  	    ]
	  },
	  "hierarchyTailorParams": {
  	    "threshold": 20
      },
	  "hitAggregatorParams": {
  	    "hitType": "indirect",
  	    "aggregationType": "mean"
      },
      "FoIMatrixType": "SingleFoIMatrix"
    }
  },
  "algorithm": {
    "name": "br.ufsc.lapesd.orbs.example.ucfmultiattribute.UCFMultiAttributeAlgorithm",
    "params": {
      "useTestSeed": false,
      "seed": 1,
      "neighborhoodSize": 100,
      "nativeEvaluatorEnabled": false,
      "iteration": 10,
      "lambda": 0.7,
      "similarItemEvents": ["view"],
      "seenItemEvents": ["view"],
      "unseenOnly": true
    }
  },
  "servingType": "br.ufsc.lapesd.orbs.tokit.Serving"
}